UART_TX_RX_VER/UART_TX_RX_VER.srcs/sources_1/new/UART_TX.v
//////////////////////////////////////////////////////////////////////
// Author: Russell Merrick
//////////////////////////////////////////////////////////////////////
// This file contains the UART Transmitter.  This transmitter is able
// to transmit 8 bits of serial data, one start bit, one stop bit,
// and no parity bit.  When transmit is complete o_Tx_done will be
// driven high for one clock cycle.
//
// Set Parameter CLKS_PER_BIT as follows:
// CLKS_PER_BIT = (Frequency of i_Clock)/(Frequency of UART)
// Example: 25 MHz Clock, 115200 baud UART
// (25000000)/(115200) = 217
`timescale 1ns/10ps

module UART_TX 
  #(parameter CLKS_PER_BIT = 217)
  (
   input       i_Rst_L,
   input       i_Clock,
   input       i_TX_DV,
   input [7:0] i_TX_Byte, 
   output reg  o_TX_Active,
   output reg  o_TX_Serial,
   output reg  o_TX_Done
   );
 
  localparam IDLE         = 3'b000;
  localparam TX_START_BIT = 3'b001;
  localparam TX_DATA_BITS = 3'b010;
  localparam TX_STOP_BIT  = 3'b011;
  localparam CLEANUP      = 3'b100;
  
  reg [2:0] r_SM_Main;
  reg [$clog2(CLKS_PER_BIT):0] r_Clock_Count;
  reg [2:0] r_Bit_Index;
  reg [7:0] r_TX_Data;


  // Purpose: Control TX state machine
  always @(posedge i_Clock or negedge i_Rst_L)
  begin
    if (~i_Rst_L)
    begin
      r_SM_Main <= 3'b000; // Set to idle
    end
    else
    begin

      o_TX_Done <= 1'b0; // default assignment

      case (r_SM_Main)
      IDLE :
        begin
          o_TX_Serial   <= 1'b1;         // Drive Line High for Idle
          r_Clock_Count <= 0;
          r_Bit_Index   <= 0;
          
          if (i_TX_DV == 1'b1)
          begin
            // Starting signal is given, set TX_data, active out and state-machine
            o_TX_Active <= 1'b1;
            r_TX_Data   <= i_TX_Byte;
            r_SM_Main   <= TX_START_BIT;
          end
          else
            r_SM_Main <= IDLE;
        end // case: IDLE
      
      
      // Send out Start Bit. Start bit = 0
      TX_START_BIT :
        begin
          o_TX_Serial <= 1'b0;
          
          // Wait CLKS_PER_BIT-1 clock cycles for start bit to finish (216 x 40 ns = 8.640 us)
          if (r_Clock_Count < CLKS_PER_BIT-1)
          begin
            r_Clock_Count <= r_Clock_Count + 1;
            r_SM_Main     <= TX_START_BIT;
          end
          else
          begin
            r_Clock_Count <= 0;
            r_SM_Main     <= TX_DATA_BITS;
          end
        end // case: TX_START_BIT
      
      
      // Wait CLKS_PER_BIT-1 clock cycles for data bits to finish         
      TX_DATA_BITS :
        begin
          // It should transmit a new bit every 8.64 us
          o_TX_Serial <= r_TX_Data[r_Bit_Index];
          
          if (r_Clock_Count < CLKS_PER_BIT-1)
          begin
            r_Clock_Count <= r_Clock_Count + 1;
            r_SM_Main     <= TX_DATA_BITS;
          end
          else
          begin
            r_Clock_Count <= 0;
            
            // Check if we have sent out all bits
            if (r_Bit_Index < 7)
            begin
              r_Bit_Index <= r_Bit_Index + 1;
              r_SM_Main   <= TX_DATA_BITS;
            end
            else
            begin
              r_Bit_Index <= 0;
              r_SM_Main   <= TX_STOP_BIT;
            end
          end 
        end // case: TX_DATA_BITS
      
      
      // Send out Stop bit.  Stop bit = 1
      TX_STOP_BIT :
        begin
          o_TX_Serial <= 1'b1;
          
          // Wait CLKS_PER_BIT-1 clock cycles for Stop bit to finish
          if (r_Clock_Count < CLKS_PER_BIT-1)
          begin
            r_Clock_Count <= r_Clock_Count + 1;
            r_SM_Main     <= TX_STOP_BIT;
          end
          else
          begin
            o_TX_Done     <= 1'b1;
            r_Clock_Count <= 0;
            r_SM_Main     <= CLEANUP;
            o_TX_Active   <= 1'b0;
          end 
        end // case: TX_STOP_BIT
      
      
      // Stay here 1 clock
      CLEANUP :
        begin
          r_SM_Main <= IDLE;
        end
      
      
      default :
        r_SM_Main <= IDLE;
      
    endcase
    end // else: !if(~i_Rst_L)
  end // always @ (posedge i_Clock or negedge i_Rst_L)

  
endmodule

UART_TX_RX_VER/UART_TX_RX_VER.srcs/sources_1/new/UART_RX.v
//////////////////////////////////////////////////////////////////////
// Author:      Russell Merrick
//////////////////////////////////////////////////////////////////////
// Description: This file contains the UART Receiver.  This receiver is 
//              able to receive 8 bits of serial data, one start bit, one 
//              stop bit, and no parity bit.  When receive is complete 
//              o_RX_DV will be driven high for one clock cycle.
// 
// Parameters:  Set Parameter CLKS_PER_BIT as follows:
//              CLKS_PER_BIT = (Frequency of i_Clock)/(Frequency of UART)
//              Example: 25 MHz Clock, 115200 baud UART
//              (25000000)/(115200) = 217
//////////////////////////////////////////////////////////////////////////////
`timescale 1ns/10ps

module UART_RX
  // parameter: constant that can be overridden during module instantiation.
  #(parameter CLKS_PER_BIT = 217)
  (
   input            i_Rst_L,
   input            i_Clock,
   input            i_RX_Serial,
   output reg       o_RX_DV, // reg: single-bit output
   output reg [7:0] o_RX_Byte // 8-bit output [MSB, LSB]
   );
  // localparam: simply a constant which stays the same inside this module, CANNOT be overridden at module instantiation (like parameter)
  localparam IDLE         = 3'b000;
  localparam RX_START_BIT = 3'b001;
  localparam RX_DATA_BITS = 3'b010;
  localparam RX_STOP_BIT  = 3'b011;
  localparam CLEANUP      = 3'b100;
  
  // $clog2(N): minimum number of bits required to represent the parameter CLKS_PER_BIT
  reg [$clog2(CLKS_PER_BIT)-1:0] r_Clock_Count;
  reg [2:0] r_Bit_Index; // 3 bits -> max 8 states
  reg [2:0] r_SM_Main; 
  reg r_RX_Data_R;
  reg r_RX_Data;
  
  // double flipflop
  always @(posedge i_Clock)
  begin
     r_RX_Data_R <= i_RX_Serial;
     r_RX_Data <= r_RX_Data_R;
  end

  
  // Purpose: Control RX state machine
  always @(posedge i_Clock or negedge i_Rst_L)
  begin
    // If ~i_Rst_L: reset is triggered
    if (~i_Rst_L)
    begin
      r_SM_Main <= 3'b000;
      o_RX_DV   <= 1'b0;
    end
    else
    begin
      case (r_SM_Main)
      IDLE :
        begin
          o_RX_DV       <= 1'b0;
          r_Clock_Count <= 0;
          r_Bit_Index   <= 0;
          
          if (r_RX_Data == 1'b0)          // Start bit detected
            r_SM_Main <= RX_START_BIT;
          else
            r_SM_Main <= IDLE;
        end
      
      // Check middle of start bit to make sure it's still low
      RX_START_BIT :
        begin
          if (r_Clock_Count == (CLKS_PER_BIT-1)/2)
          begin
            if (r_RX_Data == 1'b0)
            begin
              r_Clock_Count <= 0;  // reset counter, found the middle
              r_SM_Main     <= RX_DATA_BITS;
            end
            else
              r_SM_Main <= IDLE;
          end
          else
          begin
            r_Clock_Count <= r_Clock_Count + 1;
            r_SM_Main     <= RX_START_BIT;
          end
        end // case: RX_START_BIT
      
      
      // Wait CLKS_PER_BIT-1 clock cycles to sample serial data
      RX_DATA_BITS :
        begin
          if (r_Clock_Count < CLKS_PER_BIT-1)
          begin
            r_Clock_Count <= r_Clock_Count + 1;
            r_SM_Main     <= RX_DATA_BITS;
          end
          else
          begin
            r_Clock_Count          <= 0;
            o_RX_Byte[r_Bit_Index] <= r_RX_Data;
            
            // Check if we have received all bits
            if (r_Bit_Index < 7)
            begin
              r_Bit_Index <= r_Bit_Index + 1;
              r_SM_Main   <= RX_DATA_BITS;
            end
            else
            begin
              r_Bit_Index <= 0;
              r_SM_Main   <= RX_STOP_BIT;
            end
          end
        end // case: RX_DATA_BITS
      
      
      // Receive Stop bit.  Stop bit = 1
      RX_STOP_BIT :
        begin
          // Wait CLKS_PER_BIT-1 clock cycles for Stop bit to finish
          if (r_Clock_Count < CLKS_PER_BIT-1)
          begin
            r_Clock_Count <= r_Clock_Count + 1;
            r_SM_Main     <= RX_STOP_BIT;
          end
          else
          begin
            o_RX_DV       <= 1'b1;
            r_Clock_Count <= 0;
            r_SM_Main     <= CLEANUP;
          end
        end // case: RX_STOP_BIT
      
      
      // Stay here 1 clock
      CLEANUP :
        begin
          r_SM_Main <= IDLE;
          o_RX_DV   <= 1'b0;
        end
      
      
      default :
        r_SM_Main <= IDLE;
      
    endcase
    end // else: !if(~i_Rst_L)
  end // always @ (posedge i_Clock or negedge i_Rst_L)
  
endmodule // UART_RX

UART_TX_RX_VER/UART_TX_RX_VER.srcs/sim_1/new/UART_TB.v
//////////////////////////////////////////////////////////////////////
// File Downloaded from http://www.nandland.com
//////////////////////////////////////////////////////////////////////

// This testbench will exercise the UART RX.
// It sends out byte 0x37, and ensures the RX receives it correctly.
`timescale 1ns/10ps

`include "UART_TX.v"
`include "UART_RX.v"

module UART_TB ();

  // Testbench uses a 25 MHz clock
  // Want to interface to 115200 baud UART
  // 25000000 / 115200 = 217 Clocks Per Bit.
  parameter c_CLOCK_PERIOD_NS = 40;
  parameter c_CLKS_PER_BIT    = 217;
  parameter c_BIT_PERIOD      = 8600;
  
  reg r_Clock = 0;
  reg r_TX_DV = 0;
  wire w_TX_Active, w_UART_Line;
  wire w_TX_Serial;
  reg [7:0] r_TX_Byte = 0;
  wire [7:0] w_RX_Byte;

  UART_RX #(.CLKS_PER_BIT(c_CLKS_PER_BIT)) UART_RX_Inst
    (.i_Clock(r_Clock),
     .i_RX_Serial(w_UART_Line),
     .o_RX_DV(w_RX_DV),
     .o_RX_Byte(w_RX_Byte)
     );
  
  UART_TX #(.CLKS_PER_BIT(c_CLKS_PER_BIT)) UART_TX_Inst
    (.i_Clock(r_Clock),
     .i_TX_DV(r_TX_DV),
     .i_TX_Byte(r_TX_Byte),
     .o_TX_Active(w_TX_Active),
     .o_TX_Serial(w_TX_Serial),
     .o_TX_Done()
     );

  // Keeps the UART Receive input high (default) when
  // UART transmitter is not active
  assign w_UART_Line = w_TX_Active ? w_TX_Serial : 1'b1;

  always
    #(c_CLOCK_PERIOD_NS/2) r_Clock <= !r_Clock;
  
  // Main Testing:
  initial
    begin
      // Tell UART to send a command (exercise TX)
      @(posedge r_Clock);
      @(posedge r_Clock);
      // Start on the second positive clock edge
      r_TX_DV   <= 1'b1;
      r_TX_Byte <= 8'h4F;
      @(posedge r_Clock);
      // Set TX_DV back to zero on next clock edge
      r_TX_DV <= 1'b0;

      // Check that the correct command was received
      @(posedge w_RX_DV);
      if (w_RX_Byte == 8'h4F)
        $display("Test Passed - Correct Byte Received");
      else
        $display("Test Failed - Incorrect Byte Received");
      $finish();
    end
  
  initial 
    begin
      // Required to dump signals to EPWave
      $dumpfile("dump.vcd");
      $dumpvars(0);
    end
endmodule

UART_TX_RX_VER/UART_TX_RX_VER.sim/sim_1/behav/xsim/dump.vcd
$date
   Sun Jan 26 22:07:11 2025
$end

$version
  2023.2
  $dumpfile ("dump.vcd") 
$end

$timescale
  1ps
$end

$scope module UART_TB $end
$var reg 1 ! r_Clock $end
$var reg 1 " r_TX_DV $end
$var wire 1 # w_TX_Active $end
$var wire 1 $ w_UART_Line $end
$var wire 1 % w_TX_Serial $end
$var reg 8 & r_TX_Byte [7:0] $end
$var wire 8 ' w_RX_Byte [7:0] $end
$var wire 1 ( w_RX_DV $end
$scope module UART_RX_Inst $end
$var wire 1 ) i_Rst_L $end
$var wire 1 * i_Clock $end
$var wire 1 $ i_RX_Serial $end
$var reg 1 + o_RX_DV $end
$var reg 8 , o_RX_Byte [7:0] $end
$var reg 8 - r_Clock_Count [7:0] $end
$var reg 3 . r_Bit_Index [2:0] $end
$var reg 3 / r_SM_Main [2:0] $end
$var reg 1 0 r_RX_Data_R $end
$var reg 1 1 r_RX_Data $end
$upscope $end
$scope module UART_TX_Inst $end
$var wire 1 2 i_Rst_L $end
$var wire 1 3 i_Clock $end
$var wire 1 4 i_TX_DV $end
$var wire 8 5 i_TX_Byte [7:0] $end
$var reg 1 6 o_TX_Active $end
$var reg 1 7 o_TX_Serial $end
$var reg 1 8 o_TX_Done $end
$var reg 3 9 r_SM_Main [2:0] $end
$var reg 9 : r_Clock_Count [8:0] $end
$var reg 3 ; r_Bit_Index [2:0] $end
$var reg 8 < r_TX_Data [7:0] $end
$upscope $end
$upscope $end
$enddefinitions $end

#0
$dumpvars
0!
0"
x#
x$
x%
b0 &
bx '
x(
z)
0*
x+
bx ,
bx -
bx .
bx /
x0
x1
z2
03
04
b0 5
x6
x7
x8
bx 9
bx :
bx ;
bx <
$end

#20000
1!
1*
b0 /
13
08
b0 9

#40000
0!
0*
03

#60000
1!
1"
1$
1%
b1001111 &
0(
1*
0+
b0 -
b0 .
13
14
b1001111 5
17
b0 :
b0 ;

#80000
0!
0*
03

#100000
1!
0"
1#
1*
10
13
04
16
b1 9
b1001111 <

#120000
0!
0*
03

#140000
1!
0$
0%
1*
11
13
07
b1 :

#160000
0!
0*
03

#180000
1!
1*
00
13
b10 :

#200000
0!
0*
03

#220000
1!
1*
01
13
b11 :

#240000
0!
0*
03

#260000
1!
1*
b1 /
13
b100 :

#280000
0!
0*
03

#300000
1!
1*
b1 -
13
b101 :

#320000
0!
0*
03

#340000
1!
1*
b10 -
13
b110 :

#360000
0!
0*
03

#380000
1!
1*
b11 -
13
b111 :

#400000
0!
0*
03

#420000
1!
1*
b100 -
13
b1000 :

#440000
0!
0*
03

#460000
1!
1*
b101 -
13
b1001 :

#480000
0!
0*
03

#500000
1!
1*
b110 -
13
b1010 :

#520000
0!
0*
03

#540000
1!
1*
b111 -
13
b1011 :

#560000
0!
0*
03

#580000
1!
1*
b1000 -
13
b1100 :

#600000
0!
0*
03

#620000
1!
1*
b1001 -
13
b1101 :

#640000
0!
0*
03

#660000
1!
1*
b1010 -
13
b1110 :

#680000
0!
0*
03

#700000
1!
1*
b1011 -
13
b1111 :

#720000
0!
0*
03

#740000
1!
1*
b1100 -
13
b10000 :

#760000
0!
0*
03

#780000
1!
1*
b1101 -
13
b10001 :

#800000
0!
0*
03

#820000
1!
1*
b1110 -
13
b10010 :

#840000
0!
0*
03

#860000
1!
1*
b1111 -
13
b10011 :

#880000
0!
0*
03

#900000
1!
1*
b10000 -
13
b10100 :

#920000
0!
0*
03

#940000
1!
1*
b10001 -
13
b10101 :

#960000
0!
0*
03

#980000
1!
1*
b10010 -
13
b10110 :

